<?xml version='1.0' encoding='UTF-8'?>
<SOAP-ENV:Envelope xmlns:SOAP-ENV="http://schemas.xmlsoap.org/soap/envelope/" xmlns:xsi="http://www.w3.org/2001/XMLSchema-instance" xmlns:xsd="http://www.w3.org/2001/XMLSchema">
<SOAP-ENV:Body>
<ns1:doGoogleSearchResponse xmlns:ns1="urn:GoogleSearch" SOAP-ENV:encodingStyle="http://schemas.xmlsoap.org/soap/encoding/">
<return xsi:type="ns1:GoogleSearchResult">
<directoryCategories xmlns:ns2="http://schemas.xmlsoap.org/soap/encoding/" xsi:type="ns2:Array" ns2:arrayType="ns1:DirectoryCategory[1]">
<item xsi:type="ns1:DirectoryCategory">
<fullViewableName xsi:type="xsd:string">Top/Computers/Data_Formats/Markup_Languages/XML/Style_Sheets/XSL</fullViewableName>
<specialEncoding xsi:type="xsd:string"></specialEncoding>
</item>
</directoryCategories>
<documentFiltering xsi:type="xsd:boolean">true</documentFiltering>
<endIndex xsi:type="xsd:int">10</endIndex>
<estimateIsExact xsi:type="xsd:boolean">false</estimateIsExact>
<estimatedTotalResultsCount xsi:type="xsd:int">103000000</estimatedTotalResultsCount>
<resultElements xmlns:ns3="http://schemas.xmlsoap.org/soap/encoding/" xsi:type="ns3:Array" ns3:arrayType="ns1:ResultElement[10]">
<item xsi:type="ns1:ResultElement">
<URL xsi:type="xsd:string">http://www.w3.org/TR/xslt</URL>
<cachedSize xsi:type="xsd:string">263k</cachedSize>
<directoryCategory xsi:type="ns1:DirectoryCategory">
<fullViewableName xsi:type="xsd:string"></fullViewableName>
<specialEncoding xsi:type="xsd:string"></specialEncoding>
</directoryCategory>
<directoryTitle xsi:type="xsd:string"></directoryTitle>
<hostName xsi:type="xsd:string"></hostName>
<relatedInformationPresent xsi:type="xsd:boolean">true</relatedInformationPresent>
<snippet xsi:type="xsd:string">This specification defines the syntax and semantics of &lt;b&gt;XSLT&lt;/b&gt;, which is a language&lt;br&gt;  for transforming...</snippet>
<summary xsi:type="xsd:string"></summary>
<title xsi:type="xsd:string">XSL Transformations (&lt;b&gt;XSLT&lt;/b&gt;)</title>
</item>
<item xsi:type="ns1:ResultElement">
<URL xsi:type="xsd:string">http://www.w3.org/Style/XSL/</URL>
<cachedSize xsi:type="xsd:string">24k</cachedSize>
<directoryCategory xsi:type="ns1:DirectoryCategory">
<fullViewableName xsi:type="xsd:string"></fullViewableName>
<specialEncoding xsi:type="xsd:string"></specialEncoding>
</directoryCategory>
<directoryTitle xsi:type="xsd:string"></directoryTitle>
<hostName xsi:type="xsd:string">www.w3.org</hostName>
<relatedInformationPresent xsi:type="xsd:boolean">true</relatedInformationPresent>
<snippet xsi:type="xsd:string">An &lt;b&gt;XSLT&lt;/b&gt; stylesheet specifies the presentation of a class of XML documents by &lt;b&gt;...&lt;/b&gt;&lt;br&gt;  Stylesheet Central, a collection of over 100 examples of XML and &lt;b&gt;XSLT&lt;/b&gt; &lt;b&gt;...&lt;/b&gt;</snippet>
<summary xsi:type="xsd:string"></summary>
<title xsi:type="xsd:string">The Extensible Stylesheet Language Family (XSL)</title>
</item>
<item xsi:type="ns1:ResultElement">
<URL xsi:type="xsd:string">http://www.w3schools.com/xsl/</URL>
<cachedSize xsi:type="xsd:string">23k</cachedSize>
<directoryCategory xsi:type="ns1:DirectoryCategory">
<fullViewableName xsi:type="xsd:string"></fullViewableName>
<specialEncoding xsi:type="xsd:string"></specialEncoding>
</directoryCategory>
<directoryTitle xsi:type="xsd:string"></directoryTitle>
<hostName xsi:type="xsd:string"></hostName>
<relatedInformationPresent xsi:type="xsd:boolean">true</relatedInformationPresent>
<snippet xsi:type="xsd:string">Free HTML, XHTML, CSS, JavaScript, DHTML, XML, DOM, XSL, &lt;b&gt;XSLT&lt;/b&gt;, RSS, ASP, ADO,&lt;br&gt;  PHP, SQL tutorial, reference, examples for web building.</snippet>
<summary xsi:type="xsd:string"></summary>
<title xsi:type="xsd:string">&lt;b&gt;XSLT&lt;/b&gt; Tutorial</title>
</item>
<item xsi:type="ns1:ResultElement">
<URL xsi:type="xsd:string">http://www.zvon.org/xxl/XSLTreference/Output/index.html</URL>
<cachedSize xsi:type="xsd:string">3k</cachedSize>
<directoryCategory xsi:type="ns1:DirectoryCategory">
<fullViewableName xsi:type="xsd:string"></fullViewableName>
<specialEncoding xsi:type="xsd:string"></specialEncoding>
</directoryCategory>
<directoryTitle xsi:type="xsd:string"></directoryTitle>
<hostName xsi:type="xsd:string"></hostName>
<relatedInformationPresent xsi:type="xsd:boolean">true</relatedInformationPresent>
<snippet xsi:type="xsd:string">Complete &lt;b&gt;XSLT&lt;/b&gt; reference with links to Interactive X Lab.</snippet>
<summary xsi:type="xsd:string"></summary>
<title xsi:type="xsd:string">&lt;b&gt;XSLT&lt;/b&gt; Reference</title>
</item>
<item xsi:type="ns1:ResultElement">
<URL xsi:type="xsd:string">http://www.zvon.org/xxl/XSLTutorial/Books/Book1/index.html</URL>
<cachedSize xsi:type="xsd:string">2k</cachedSize>
<directoryCategory xsi:type="ns1:DirectoryCategory">
<fullViewableName xsi:type="xsd:string"></fullViewableName>
<specialEncoding xsi:type="xsd:string"></specialEncoding>
</directoryCategory>
<directoryTitle xsi:type="xsd:string"></directoryTitle>
<hostName xsi:type="xsd:string"></hostName>
<relatedInformationPresent xsi:type="xsd:boolean">true</relatedInformationPresent>
<snippet xsi:type="xsd:string">Interactive XSL training by examples.</snippet>
<summary xsi:type="xsd:string"></summary>
<title xsi:type="xsd:string">&lt;b&gt;XSLT&lt;/b&gt; Tutorial</title>
</item>
<item xsi:type="ns1:ResultElement">
<URL xsi:type="xsd:string">http://www.xslt.com/</URL>
<cachedSize xsi:type="xsd:string">5k</cachedSize>
<directoryCategory xsi:type="ns1:DirectoryCategory">
<fullViewableName xsi:type="xsd:string"></fullViewableName>
<specialEncoding xsi:type="xsd:string"></specialEncoding>
</directoryCategory>
<directoryTitle xsi:type="xsd:string"></directoryTitle>
<hostName xsi:type="xsd:string"></hostName>
<relatedInformationPresent xsi:type="xsd:boolean">true</relatedInformationPresent>
<snippet xsi:type="xsd:string">(&lt;b&gt;XSLT&lt;/b&gt;.com promises never give your email to spammers). &lt;b&gt;XSLT&lt;/b&gt;.com is a site dedicated&lt;br&gt;  to providing &lt;b&gt;XSLT&lt;/b&gt;, XPath and some XSL:FO infrormation for programmers. &lt;b&gt;...&lt;/b&gt;</snippet>
<summary xsi:type="xsd:string"></summary>
<title xsi:type="xsd:string">&lt;b&gt;XSLT&lt;/b&gt;</title>
</item>
<item xsi:type="ns1:ResultElement">
<URL xsi:type="xsd:string">http://en.wikipedia.org/wiki/XSLT</URL>
<cachedSize xsi:type="xsd:string">49k</cachedSize>
<directoryCategory xsi:type="ns1:DirectoryCategory">
<fullViewableName xsi:type="xsd:string"></fullViewableName>
<specialEncoding xsi:type="xsd:string"></specialEncoding>
</directoryCategory>
<directoryTitle xsi:type="xsd:string"></directoryTitle>
<hostName xsi:type="xsd:string"></hostName>
<relatedInformationPresent xsi:type="xsd:boolean">true</relatedInformationPresent>
<snippet xsi:type="xsd:string">Extensible Stylesheet Language Transformations, or &lt;b&gt;XSLT&lt;/b&gt;, is an XML-based &lt;b&gt;...&lt;/b&gt;&lt;br&gt;  &lt;b&gt;XSLT&lt;/b&gt; was produced as a result of the Extensible Stylesheet Language (XSL) &lt;b&gt;...&lt;/b&gt;</snippet>
<summary xsi:type="xsd:string"></summary>
<title xsi:type="xsd:string">XSL Transformations - Wikipedia, the free encyclopedia</title>
</item>
<item xsi:type="ns1:ResultElement">
<URL xsi:type="xsd:string">http://saxon.sourceforge.net/</URL>
<cachedSize xsi:type="xsd:string">11k</cachedSize>
<directoryCategory xsi:type="ns1:DirectoryCategory">
<fullViewableName xsi:type="xsd:string"></fullViewableName>
<specialEncoding xsi:type="xsd:string"></specialEncoding>
</directoryCategory>
<directoryTitle xsi:type="xsd:string"></directoryTitle>
<hostName xsi:type="xsd:string"></hostName>
<relatedInformationPresent xsi:type="xsd:boolean">true</relatedInformationPresent>
<snippet xsi:type="xsd:string">Java &lt;b&gt;XSLT&lt;/b&gt; processor developed by Michael Kay [Open source, MPL].</snippet>
<summary xsi:type="xsd:string"></summary>
<title xsi:type="xsd:string">The SAXON &lt;b&gt;XSLT&lt;/b&gt; and XQuery Processor</title>
</item>
<item xsi:type="ns1:ResultElement">
<URL xsi:type="xsd:string">http://xml.apache.org/xalan-j/</URL>
<cachedSize xsi:type="xsd:string">50k</cachedSize>
<directoryCategory xsi:type="ns1:DirectoryCategory">
<fullViewableName xsi:type="xsd:string"></fullViewableName>
<specialEncoding xsi:type="xsd:string"></specialEncoding>
</directoryCategory>
<directoryTitle xsi:type="xsd:string"></directoryTitle>
<hostName xsi:type="xsd:string"></hostName>
<relatedInformationPresent xsi:type="xsd:boolean">true</relatedInformationPresent>
<snippet xsi:type="xsd:string">Xalan is an &lt;b&gt;XSLT&lt;/b&gt; (Extensible Stylesheet Language Transformation) processor for&lt;br&gt;  transforming XML documents...</snippet>
<summary xsi:type="xsd:string"></summary>
<title xsi:type="xsd:string">Xalan-Java Version 2.7.0</title>
</item>
<item xsi:type="ns1:ResultElement">
<URL xsi:type="xsd:string">http://xmlsoft.org/XSLT/</URL>
<cachedSize xsi:type="xsd:string">7k</cachedSize>
<directoryCategory xsi:type="ns1:DirectoryCategory">
<fullViewableName xsi:type="xsd:string"></fullViewableName>
<specialEncoding xsi:type="xsd:string"></specialEncoding>
</directoryCategory>
<directoryTitle xsi:type="xsd:string"></directoryTitle>
<hostName xsi:type="xsd:string"></hostName>
<relatedInformationPresent xsi:type="xsd:boolean">true</relatedInformationPresent>
<snippet xsi:type="xsd:string">Libxslt is the &lt;b&gt;XSLT&lt;/b&gt; C library developed for the Gnome project. Libxslt is based&lt;br&gt;  on libxml2 the XML...</snippet>
<summary xsi:type="xsd:string"></summary>
<title xsi:type="xsd:string">Libxslt - the &lt;b&gt;XSLT&lt;/b&gt; C library for Gnome</title>
</item>
</resultElements>
<searchComments xsi:type="xsd:string"></searchComments>
<searchQuery xsi:type="xsd:string">xslt</searchQuery>
<searchTime xsi:type="xsd:double">0.144656</searchTime>
<searchTips xsi:type="xsd:string"></searchTips>
<startIndex xsi:type="xsd:int">1</startIndex>
</return>
</ns1:doGoogleSearchResponse>

</SOAP-ENV:Body>
</SOAP-ENV:Envelope>


