<?xml version='1.0' encoding='UTF-8'?>
<SOAP-ENV:Envelope xmlns:SOAP-ENV="http://schemas.xmlsoap.org/soap/envelope/" xmlns:xsi="http://www.w3.org/1999/XMLSchema-instance" xmlns:xsd="http://www.w3.org/1999/XMLSchema">
<SOAP-ENV:Body>
<ns1:doGoogleSearchResponse xmlns:ns1="urn:GoogleSearch" SOAP-ENV:encodingStyle="http://schemas.xmlsoap.org/soap/encoding/">
<return xsi:type="ns1:GoogleSearchResult">
<directoryCategories xmlns:ns2="http://schemas.xmlsoap.org/soap/encoding/" xsi:type="ns2:Array" ns2:arrayType="ns1:DirectoryCategory[1]">
<item xsi:type="ns1:DirectoryCategory">
<fullViewableName xsi:type="xsd:string">Top/Computers/Security/Internet</fullViewableName>
<specialEncoding xsi:type="xsd:string"></specialEncoding>
</item>
</directoryCategories>
<documentFiltering xsi:type="xsd:boolean">true</documentFiltering>
<endIndex xsi:type="xsd:int">10</endIndex>
<estimateIsExact xsi:type="xsd:boolean">false</estimateIsExact>
<estimatedTotalResultsCount xsi:type="xsd:int">454000000</estimatedTotalResultsCount>
<resultElements xmlns:ns3="http://schemas.xmlsoap.org/soap/encoding/" xsi:type="ns3:Array" ns3:arrayType="ns1:ResultElement[10]">
<item xsi:type="ns1:ResultElement">
<URL xsi:type="xsd:string">http://xml.apache.org/security/</URL>
<cachedSize xsi:type="xsd:string">11k</cachedSize>
<directoryCategory xsi:type="ns1:DirectoryCategory">
<fullViewableName xsi:type="xsd:string"></fullViewableName>
<specialEncoding xsi:type="xsd:string"></specialEncoding>
</directoryCategory>
<directoryTitle xsi:type="xsd:string"></directoryTitle>
<hostName xsi:type="xsd:string"></hostName>
<relatedInformationPresent xsi:type="xsd:boolean">true</relatedInformationPresent>
<snippet xsi:type="xsd:string">The &lt;b&gt;XML Security&lt;/b&gt; project is aimed at providing implementation of &lt;b&gt;security&lt;/b&gt; standards&lt;br&gt;  for &lt;b&gt;XML&lt;/b&gt;. Currently the focus is on the W3C standards : &lt;b&gt;...&lt;/b&gt;</snippet>
<summary xsi:type="xsd:string"></summary>
<title xsi:type="xsd:string">Welcome to &lt;b&gt;XML Security&lt;/b&gt;</title>
</item>
<item xsi:type="ns1:ResultElement">
<URL xsi:type="xsd:string">http://www.alphaworks.ibm.com/tech/xmlsecuritysuite</URL>
<cachedSize xsi:type="xsd:string">24k</cachedSize>
<directoryCategory xsi:type="ns1:DirectoryCategory">
<fullViewableName xsi:type="xsd:string"></fullViewableName>
<specialEncoding xsi:type="xsd:string"></specialEncoding>
</directoryCategory>
<directoryTitle xsi:type="xsd:string"></directoryTitle>
<hostName xsi:type="xsd:string"></hostName>
<relatedInformationPresent xsi:type="xsd:boolean">true</relatedInformationPresent>
<snippet xsi:type="xsd:string">A tool that provides &lt;b&gt;security&lt;/b&gt; features such as digital signature, encryption,&lt;br&gt;  and access control for &lt;b&gt;XML&lt;/b&gt; documents.</snippet>
<summary xsi:type="xsd:string"></summary>
<title xsi:type="xsd:string">alphaWorks : &lt;b&gt;XML Security&lt;/b&gt; Suite : Overview</title>
</item>
<item xsi:type="ns1:ResultElement">
<URL xsi:type="xsd:string">http://www.xml.org/xml/resources_focus_security.shtml</URL>
<cachedSize xsi:type="xsd:string">19k</cachedSize>
<directoryCategory xsi:type="ns1:DirectoryCategory">
<fullViewableName xsi:type="xsd:string"></fullViewableName>
<specialEncoding xsi:type="xsd:string"></specialEncoding>
</directoryCategory>
<directoryTitle xsi:type="xsd:string"></directoryTitle>
<hostName xsi:type="xsd:string"></hostName>
<relatedInformationPresent xsi:type="xsd:boolean">true</relatedInformationPresent>
<snippet xsi:type="xsd:string">An Entrust White Paper: Web Services Trust &amp;amp; &lt;b&gt;XML Security&lt;/b&gt; Standards &lt;b&gt;...&lt;/b&gt; &lt;b&gt;XML Security&lt;/b&gt;&lt;br&gt;  Specifications &lt;b&gt;XML&lt;/b&gt;-Signature Syntax and Processing &lt;b&gt;...&lt;/b&gt;</snippet>
<summary xsi:type="xsd:string"></summary>
<title xsi:type="xsd:string">&lt;b&gt;XML&lt;/b&gt;.org</title>
</item>
<item xsi:type="ns1:ResultElement">
<URL xsi:type="xsd:string">http://www.aleksey.com/xmlsec/</URL>
<cachedSize xsi:type="xsd:string">6k</cachedSize>
<directoryCategory xsi:type="ns1:DirectoryCategory">
<fullViewableName xsi:type="xsd:string"></fullViewableName>
<specialEncoding xsi:type="xsd:string"></specialEncoding>
</directoryCategory>
<directoryTitle xsi:type="xsd:string"></directoryTitle>
<hostName xsi:type="xsd:string"></hostName>
<relatedInformationPresent xsi:type="xsd:boolean">true</relatedInformationPresent>
<snippet xsi:type="xsd:string">&lt;b&gt;XML Security&lt;/b&gt; Library is released under the MIT Licence see the Copyright file&lt;br&gt;  &lt;b&gt;...&lt;/b&gt; The new &lt;b&gt;XML Security&lt;/b&gt; Library 1.2.9 release includes few bug fixes and adds &lt;b&gt;...&lt;/b&gt;</snippet>
<summary xsi:type="xsd:string"></summary>
<title xsi:type="xsd:string">&lt;b&gt;XML Security&lt;/b&gt; Library</title>
</item>
<item xsi:type="ns1:ResultElement">
<URL xsi:type="xsd:string">http://www.aleksey.com/cgi-bin/books.cgi?ASIN=0072193999</URL>
<cachedSize xsi:type="xsd:string">108k</cachedSize>
<directoryCategory xsi:type="ns1:DirectoryCategory">
<fullViewableName xsi:type="xsd:string"></fullViewableName>
<specialEncoding xsi:type="xsd:string"></specialEncoding>
</directoryCategory>
<directoryTitle xsi:type="xsd:string"></directoryTitle>
<hostName xsi:type="xsd:string"></hostName>
<relatedInformationPresent xsi:type="xsd:boolean">true</relatedInformationPresent>
<snippet xsi:type="xsd:string">Amazon.com: &lt;b&gt;XML Security&lt;/b&gt;: Books: Blake Dournaee by Blake Dournaee.</snippet>
<summary xsi:type="xsd:string"></summary>
<title xsi:type="xsd:string">Amazon.com: &lt;b&gt;XML Security&lt;/b&gt;: Books: Blake Dournaee</title>
</item>
<item xsi:type="ns1:ResultElement">
<URL xsi:type="xsd:string">http://www.dcs.uni-siegen.de/~geuer-pollmann/xml_security.html</URL>
<cachedSize xsi:type="xsd:string">80k</cachedSize>
<directoryCategory xsi:type="ns1:DirectoryCategory">
<fullViewableName xsi:type="xsd:string"></fullViewableName>
<specialEncoding xsi:type="xsd:string"></specialEncoding>
</directoryCategory>
<directoryTitle xsi:type="xsd:string"></directoryTitle>
<hostName xsi:type="xsd:string"></hostName>
<relatedInformationPresent xsi:type="xsd:boolean">true</relatedInformationPresent>
<snippet xsi:type="xsd:string">This article is not about &lt;b&gt;XML Security&lt;/b&gt;, but about EDI &lt;b&gt;security&lt;/b&gt;. &lt;b&gt;...&lt;/b&gt; 2002-08-20:&lt;br&gt;  Tutorial: Getting Started With &lt;b&gt;XML Security&lt;/b&gt; by Frederick Hirsch &lt;b&gt;...&lt;/b&gt;</snippet>
<summary xsi:type="xsd:string"></summary>
<title xsi:type="xsd:string">&lt;b&gt;XML Security&lt;/b&gt; page</title>
</item>
<item xsi:type="ns1:ResultElement">
<URL xsi:type="xsd:string">http://www.itarchitect.com/article/NMG20010518S0010</URL>
<cachedSize xsi:type="xsd:string"></cachedSize>
<directoryCategory xsi:type="ns1:DirectoryCategory">
<fullViewableName xsi:type="xsd:string"></fullViewableName>
<specialEncoding xsi:type="xsd:string"></specialEncoding>
</directoryCategory>
<directoryTitle xsi:type="xsd:string"></directoryTitle>
<hostName xsi:type="xsd:string"></hostName>
<relatedInformationPresent xsi:type="xsd:boolean">true</relatedInformationPresent>
<snippet xsi:type="xsd:string">While &lt;b&gt;XML&lt;/b&gt; documents must be protected from prying eyes and the corrupting influences&lt;br&gt;  of the Internet, &lt;b&gt;XML&lt;/b&gt; can also be a &lt;b&gt;security&lt;/b&gt; tool for many applications.</snippet>
<summary xsi:type="xsd:string"></summary>
<title xsi:type="xsd:string">IT Architect | Special Report: The Language Of &lt;b&gt;XML Security&lt;/b&gt; | June &lt;b&gt;...&lt;/b&gt;</title>
</item>
<item xsi:type="ns1:ResultElement">
<URL xsi:type="xsd:string">http://techupdate.zdnet.com/techupdate/stories/main/0,14179,2873295,00.html</URL>
<cachedSize xsi:type="xsd:string">35k</cachedSize>
<directoryCategory xsi:type="ns1:DirectoryCategory">
<fullViewableName xsi:type="xsd:string"></fullViewableName>
<specialEncoding xsi:type="xsd:string"></specialEncoding>
</directoryCategory>
<directoryTitle xsi:type="xsd:string"></directoryTitle>
<hostName xsi:type="xsd:string"></hostName>
<relatedInformationPresent xsi:type="xsd:boolean">true</relatedInformationPresent>
<snippet xsi:type="xsd:string">Similar in concept to &lt;b&gt;security&lt;/b&gt; certificate signatures, &lt;b&gt;XML&lt;/b&gt; signatures are used&lt;br&gt;  to ensure that &lt;b&gt;...&lt;/b&gt; Demand for &lt;b&gt;XML security&lt;/b&gt; increases as &lt;b&gt;XML&lt;/b&gt; usage spreads. &lt;b&gt;...&lt;/b&gt;</snippet>
<summary xsi:type="xsd:string"></summary>
<title xsi:type="xsd:string">&lt;b&gt;XML security&lt;/b&gt;: A who&amp;#39;s who - TechUpdate - ZDNet</title>
</item>
<item xsi:type="ns1:ResultElement">
<URL xsi:type="xsd:string">http://www.datapower.com/products/xs40.html</URL>
<cachedSize xsi:type="xsd:string">27k</cachedSize>
<directoryCategory xsi:type="ns1:DirectoryCategory">
<fullViewableName xsi:type="xsd:string"></fullViewableName>
<specialEncoding xsi:type="xsd:string"></specialEncoding>
</directoryCategory>
<directoryTitle xsi:type="xsd:string"></directoryTitle>
<hostName xsi:type="xsd:string"></hostName>
<relatedInformationPresent xsi:type="xsd:boolean">true</relatedInformationPresent>
<snippet xsi:type="xsd:string">An &lt;b&gt;XML security&lt;/b&gt; appliance which supports WS-&lt;b&gt;Security&lt;/b&gt;, SAML, &lt;b&gt;XML&lt;/b&gt; Firewall, &lt;b&gt;XML&lt;/b&gt;&lt;br&gt;  Signature, &lt;b&gt;XML&lt;/b&gt; Encryption, &lt;b&gt;XML&lt;/b&gt; Schema, XPath filtering, SOAP, XSLT, &lt;b&gt;XML&lt;/b&gt; Proxy, &lt;b&gt;...&lt;/b&gt;</snippet>
<summary xsi:type="xsd:string"></summary>
<title xsi:type="xsd:string">DataPower: XS40 &lt;b&gt;XML Security&lt;/b&gt; Gateway</title>
</item>
<item xsi:type="ns1:ResultElement">
<URL xsi:type="xsd:string">http://www.oasis-open.org/committees/security/</URL>
<cachedSize xsi:type="xsd:string">51k</cachedSize>
<directoryCategory xsi:type="ns1:DirectoryCategory">
<fullViewableName xsi:type="xsd:string"></fullViewableName>
<specialEncoding xsi:type="xsd:string"></specialEncoding>
</directoryCategory>
<directoryTitle xsi:type="xsd:string"></directoryTitle>
<hostName xsi:type="xsd:string"></hostName>
<relatedInformationPresent xsi:type="xsd:boolean">true</relatedInformationPresent>
<snippet xsi:type="xsd:string">SAML, developed by the &lt;b&gt;Security&lt;/b&gt; Services Technical Committee of OASIS, is an&lt;br&gt;  &lt;b&gt;XML&lt;/b&gt;-based framework for communicating user authentication, entitlement, &lt;b&gt;...&lt;/b&gt;</snippet>
<summary xsi:type="xsd:string"></summary>
<title xsi:type="xsd:string">OASIS &lt;b&gt;Security&lt;/b&gt; Services (SAML) TC</title>
</item>
</resultElements>
<searchComments xsi:type="xsd:string"></searchComments>
<searchQuery xsi:type="xsd:string">xml security</searchQuery>
<searchTime xsi:type="xsd:double">0.237541</searchTime>
<searchTips xsi:type="xsd:string"></searchTips>
<startIndex xsi:type="xsd:int">1</startIndex>
</return>
</ns1:doGoogleSearchResponse>

</SOAP-ENV:Body>
</SOAP-ENV:Envelope>


