<?xml version="1.0" encoding="UTF-8"?><ESGMain xmlns:esg="urn:dvb:ipdc:esg:2005" xmlns:xsi="http://www.w3.org/2001/XMLSchema-instance" xmlns="urn:dvb:ipdc:esg:2005" xmlns:tva="urn:tva:metadata:2005" xmlns:mpeg7="urn:mpeg:mpeg7:schema:2001" xsi:schemaLocation="urn:dvb:ipdc:esg:2005 ../schemas/dvb_ipdc_esg.xsd"><CopyrightNotice>
        "supported by BBC Backstage" - http://backstage.bbc.co.uk/data/TvChannelFeeds
        This data is strictly for non-commercial use only.
        ---
        See http://backstage.bbc.co.uk/archives/2005/01/terms_of_use.html 
        for details of the terms and conditions.
      </CopyrightNotice><ESG><ServiceTable><Service serviceID="BBCOne" freeToAir="true"><ServiceName>BBC One</ServiceName><ServiceLogo><mpeg7:TitleImage><mpeg7:MediaUri>logo/BBCOne.gif</mpeg7:MediaUri></mpeg7:TitleImage></ServiceLogo><ServiceGenre type="main" href="urn:tva:metadata:cs:MediaTypeCS:2004:7.1.3"><tva:Name>Audio and video</tva:Name></ServiceGenre><AcquisitionRef IDRef="BBCOne_acq"/></Service><Service serviceID="BBCTwo" freeToAir="true"><ServiceName>BBC Two</ServiceName><ServiceLogo><mpeg7:TitleImage><mpeg7:MediaUri>logo/BBCTwo.gif</mpeg7:MediaUri></mpeg7:TitleImage></ServiceLogo><ServiceGenre type="main" href="urn:tva:metadata:cs:MediaTypeCS:2004:7.1.3"><tva:Name>Audio and video</tva:Name></ServiceGenre><AcquisitionRef IDRef="BBCTwo_acq"/></Service><Service serviceID="BBCNewsTF" freeToAir="true"><ServiceName>BBC News 24</ServiceName><ServiceLogo><mpeg7:TitleImage><mpeg7:MediaUri>logo/BBCNewsTF.gif</mpeg7:MediaUri></mpeg7:TitleImage></ServiceLogo><ServiceGenre type="main" href="urn:tva:metadata:cs:MediaTypeCS:2004:7.1.3"><tva:Name>Audio and video</tva:Name></ServiceGenre><ServiceGenre type="main" href="urn:tva:metadata:cs:ContentCS:2004:3.1.1"><tva:Name>News</tva:Name></ServiceGenre><AcquisitionRef IDRef="BBCNewsTF_acq"/></Service><Service serviceID="BBCThree" freeToAir="true"><ServiceName>BBC Three</ServiceName><ServiceLogo><mpeg7:TitleImage><mpeg7:MediaUri>logo/BBCThree.gif</mpeg7:MediaUri></mpeg7:TitleImage></ServiceLogo><ServiceGenre type="main" href="urn:tva:metadata:cs:MediaTypeCS:2004:7.1.3"><tva:Name>Audio and video</tva:Name></ServiceGenre><ServiceGenre type="main" href="urn:tva:metadata:cs:IntendedAudienceCS:2004:4.2.2.2"><tva:Name>age 18-20</tva:Name></ServiceGenre><ServiceGenre type="main" href="urn:tva:metadata:cs:IntendedAudienceCS:2004:4.2.2.3"><tva:Name>age 21-24</tva:Name></ServiceGenre><AcquisitionRef IDRef="BBCThree_acq"/></Service><Service serviceID="BBCFour" freeToAir="true"><ServiceName>BBC Four</ServiceName><ServiceLogo><mpeg7:TitleImage><mpeg7:MediaUri>logo/BBCFour.gif</mpeg7:MediaUri></mpeg7:TitleImage></ServiceLogo><ServiceGenre type="main" href="urn:tva:metadata:cs:MediaTypeCS:2004:7.1.3"><tva:Name>Audio and video</tva:Name></ServiceGenre><AcquisitionRef IDRef="BBCFour_acq"/></Service><Service serviceID="BBCCBBC" freeToAir="true"><ServiceName>CBBC</ServiceName><ServiceLogo><mpeg7:TitleImage><mpeg7:MediaUri>logo/BBCCBBC.gif</mpeg7:MediaUri></mpeg7:TitleImage></ServiceLogo><ServiceGenre type="main" href="urn:tva:metadata:cs:MediaTypeCS:2004:7.1.3"><tva:Name>Audio and video</tva:Name></ServiceGenre><ServiceGenre type="main" href="urn:tva:metadata:cs:IntendedAudienceCS:2004:4.2.1.2"><tva:Name>age 8-13</tva:Name></ServiceGenre><ServiceGenre type="main" href="urn:tva:metadata:cs:IntendedAudienceCS:2004:4.2.1.3"><tva:Name>age 14-15</tva:Name></ServiceGenre><AcquisitionRef IDRef="BBCCBBC_acq"/></Service><Service serviceID="BBCCbeebies" freeToAir="true"><ServiceName>Cbeebies</ServiceName><ServiceLogo><mpeg7:TitleImage><mpeg7:MediaUri>logo/BBCCbeebies.gif</mpeg7:MediaUri></mpeg7:TitleImage></ServiceLogo><ServiceGenre type="main" href="urn:tva:metadata:cs:MediaTypeCS:2004:7.1.3"><tva:Name>Audio and video</tva:Name></ServiceGenre><ServiceGenre type="main" href="urn:tva:metadata:cs:IntendedAudienceCS:2004:4.2.1.1"><tva:Name>age 4-7</tva:Name></ServiceGenre><AcquisitionRef IDRef="BBCCbeebies_acq"/></Service><Service serviceID="BBCParl" freeToAir="true"><ServiceName>BBC Parliament</ServiceName><ServiceLogo><mpeg7:TitleImage><mpeg7:MediaUri>logo/BBCParl.gif</mpeg7:MediaUri></mpeg7:TitleImage></ServiceLogo><ServiceGenre type="main" href="urn:tva:metadata:cs:MediaTypeCS:2004:7.1.3"><tva:Name>Audio and video</tva:Name></ServiceGenre><ServiceGenre type="main" href="urn:tva:metadata:cs:ContentCS:2004:3.1.1.6"><tva:Name>National politics/National Assembly</tva:Name></ServiceGenre><ServiceGenre type="main" href="urn:tva:metadata:cs:ContentCS:2004:3.1.3.1"><tva:Name>Political</tva:Name></ServiceGenre><AcquisitionRef IDRef="BBCParl_acq"/></Service><Service serviceID="BBCWrld" freeToAir="true"><ServiceName>BBC World Service</ServiceName><ServiceLogo><mpeg7:TitleImage><mpeg7:MediaUri>logo/BBCWrld.gif</mpeg7:MediaUri></mpeg7:TitleImage></ServiceLogo><ServiceGenre type="main" href="urn:tva:metadata:cs:MediaTypeCS:2004:7.1.1"><tva:Name>Audio only</tva:Name></ServiceGenre><AcquisitionRef IDRef="BBCWrld_acq"/></Service><Service serviceID="BBCROne" freeToAir="true"><ServiceName>BBC Radio 1</ServiceName><ServiceLogo><mpeg7:TitleImage><mpeg7:MediaUri>logo/BBCROne.gif</mpeg7:MediaUri></mpeg7:TitleImage></ServiceLogo><ServiceGenre type="main" href="urn:tva:metadata:cs:MediaTypeCS:2004:7.1.1"><tva:Name>Audio only</tva:Name></ServiceGenre><ServiceGenre type="main" href="urn:tva:metadata:cs:ContentCS:2004:3.6.4"><tva:Name>Pop-rock</tva:Name></ServiceGenre><AcquisitionRef IDRef="BBCROne_acq"/></Service><Service serviceID="BBCRTwo" freeToAir="true"><ServiceName>BBC Radio 2</ServiceName><ServiceLogo><mpeg7:TitleImage><mpeg7:MediaUri>logo/BBCRTwo.gif</mpeg7:MediaUri></mpeg7:TitleImage></ServiceLogo><ServiceGenre type="main" href="urn:tva:metadata:cs:MediaTypeCS:2004:7.1.1"><tva:Name>Audio only</tva:Name></ServiceGenre><ServiceGenre type="main" href="urn:tva:metadata:cs:ContentCS:2004:3.6.3.2"><tva:Name>Easy listening</tva:Name></ServiceGenre><AcquisitionRef IDRef="BBCRTwo_acq"/></Service><Service serviceID="BBCRThree" freeToAir="true"><ServiceName>BBC Radio 3</ServiceName><ServiceLogo><mpeg7:TitleImage><mpeg7:MediaUri>logo/BBCRThree.gif</mpeg7:MediaUri></mpeg7:TitleImage></ServiceLogo><ServiceGenre type="main" href="urn:tva:metadata:cs:MediaTypeCS:2004:7.1.1"><tva:Name>Audio only</tva:Name></ServiceGenre><ServiceGenre type="main" href="urn:tva:metadata:cs:ContentCS:2004:3.6.14.4"><tva:Name>Classical</tva:Name></ServiceGenre><ServiceGenre type="main" href="urn:tva:metadata:cs:ContentCS:2004:3.6.2"><tva:Name>Jazz</tva:Name></ServiceGenre><AcquisitionRef IDRef="BBCRThree_acq"/></Service><Service serviceID="BBCRFour" freeToAir="true"><ServiceName>BBC Radio 4</ServiceName><ServiceLogo><mpeg7:TitleImage><mpeg7:MediaUri>logo/BBCRFour.gif</mpeg7:MediaUri></mpeg7:TitleImage></ServiceLogo><ServiceGenre type="main" href="urn:tva:metadata:cs:MediaTypeCS:2004:7.1.1"><tva:Name>Audio only</tva:Name></ServiceGenre><AcquisitionRef IDRef="BBCRFour_acq"/></Service><Service serviceID="BBCRFiveL" freeToAir="true"><ServiceName>BBC Radio 5 Live</ServiceName><ServiceLogo><mpeg7:TitleImage><mpeg7:MediaUri>logo/BBCRFiveL.gif</mpeg7:MediaUri></mpeg7:TitleImage></ServiceLogo><ServiceGenre type="main" href="urn:tva:metadata:cs:MediaTypeCS:2004:7.1.1"><tva:Name>Audio only</tva:Name></ServiceGenre><AcquisitionRef IDRef="BBCRFiveL_acq"/></Service><Service serviceID="BBCRFiveX" freeToAir="true"><ServiceName>BBC Radio 5 Extra</ServiceName><ServiceLogo><mpeg7:TitleImage><mpeg7:MediaUri>logo/BBCRFiveX.gif</mpeg7:MediaUri></mpeg7:TitleImage></ServiceLogo><ServiceGenre type="main" href="urn:tva:metadata:cs:MediaTypeCS:2004:7.1.1"><tva:Name>Audio only</tva:Name></ServiceGenre><AcquisitionRef IDRef="BBCRFiveX_acq"/></Service><Service serviceID="BBCSixMU" freeToAir="true"><ServiceName>BBC Radio 6 Music</ServiceName><ServiceLogo><mpeg7:TitleImage><mpeg7:MediaUri>logo/BBCSixMU.gif</mpeg7:MediaUri></mpeg7:TitleImage></ServiceLogo><ServiceGenre type="main" href="urn:tva:metadata:cs:MediaTypeCS:2004:7.1.1"><tva:Name>Audio only</tva:Name></ServiceGenre><ServiceGenre type="main" href="urn:tva:metadata:cs:ContentCS:2004:3.6"><tva:Name>MUSIC</tva:Name></ServiceGenre><AcquisitionRef IDRef="BBCSixMU_acq"/></Service><Service serviceID="OneXtra" freeToAir="true"><ServiceName>1Xtra</ServiceName><ServiceLogo><mpeg7:TitleImage><mpeg7:MediaUri>logo/OneXtra.gif</mpeg7:MediaUri></mpeg7:TitleImage></ServiceLogo><ServiceGenre type="main" href="urn:tva:metadata:cs:MediaTypeCS:2004:7.1.1"><tva:Name>Audio only</tva:Name></ServiceGenre><ServiceGenre type="main" href="urn:tva:metadata:cs:ContentCS:2004:3.6"><tva:Name>MUSIC</tva:Name></ServiceGenre><AcquisitionRef IDRef="OneXtra_acq"/></Service><Service serviceID="BBCSeven" freeToAir="true"><ServiceName>BBC Seven Digital</ServiceName><ServiceLogo><mpeg7:TitleImage><mpeg7:MediaUri>logo/BBCSeven.gif</mpeg7:MediaUri></mpeg7:TitleImage></ServiceLogo><ServiceGenre type="main" href="urn:tva:metadata:cs:MediaTypeCS:2004:7.1.1"><tva:Name>Audio only</tva:Name></ServiceGenre><AcquisitionRef IDRef="BBCSeven_acq"/></Service><Service serviceID="BBCAsian" freeToAir="true"><ServiceName>BBC Asian</ServiceName><ServiceLogo><mpeg7:TitleImage><mpeg7:MediaUri>logo/BBCAsian.gif</mpeg7:MediaUri></mpeg7:TitleImage></ServiceLogo><ServiceGenre type="main" href="urn:tva:metadata:cs:MediaTypeCS:2004:7.1.1"><tva:Name>Audio only</tva:Name></ServiceGenre><ServiceGenre type="main" href="urn:tva:metadata:cs:IntendedAudienceCS:2004:4.3.1"><tva:Name>Ethnic</tva:Name></ServiceGenre><AcquisitionRef IDRef="BBCAsian_acq"/></Service></ServiceTable><AcquisitionTable><Acquisition acquisitionID="BBCOne_acq" contentMimeType="application/octet-stream"><ComponentDescription><SessionDescription xsi:type="esg:InlinedSDPType"><SDP>v=0&#xD;
o=cbmshost 2890844526 2890842807 IN IP4 192.168.0.2&#xD;
s=Expway SDP Example&#xD;
i=Example of SDP file for &#xD;
u=http://www.expway.com/&#xD;
c=IN IP4 225.224.1.1&#xD;
t=0 0&#xD;
m=video 4002 RTP/AVP  96&#xD;
a=rtpmap:96 H264/90000&#xD;
a=fmtp:96 profile-level-id=42A01E; packetization-mode=1; sprop-parameter-sets=Z0IACpZTBYmI,aMljiA==&#xD;
m=audio 4004 RTP/AVP  98&#xD;
a=rtpmap:98 AMR/8000&#xD;
a=fmtp:98 octet-align=1&#xD;
</SDP></SessionDescription></ComponentDescription></Acquisition><Acquisition acquisitionID="BBCTwo_acq" contentMimeType="application/octet-stream"><ComponentDescription><SessionDescription xsi:type="esg:InlinedSDPType"><SDP>v=0&#xD;
o=cbmshost 2890844526 2890842807 IN IP4 192.168.0.2&#xD;
s=Expway SDP Example&#xD;
i=Example of SDP file for &#xD;
u=http://www.expway.com/&#xD;
c=IN IP4 225.224.1.1&#xD;
t=0 0&#xD;
m=video 4002 RTP/AVP  96&#xD;
a=rtpmap:96 H264/90000&#xD;
a=fmtp:96 profile-level-id=42A01E; packetization-mode=1; sprop-parameter-sets=Z0IACpZTBYmI,aMljiA==&#xD;
m=audio 4004 RTP/AVP  98&#xD;
a=rtpmap:98 AMR/8000&#xD;
a=fmtp:98 octet-align=1&#xD;
</SDP></SessionDescription></ComponentDescription></Acquisition><Acquisition acquisitionID="BBCNewsTF_acq" contentMimeType="application/octet-stream"><ComponentDescription><SessionDescription xsi:type="esg:InlinedSDPType"><SDP>v=0&#xD;
o=cbmshost 2890844526 2890842807 IN IP4 192.168.0.2&#xD;
s=Expway SDP Example&#xD;
i=Example of SDP file for &#xD;
u=http://www.expway.com/&#xD;
c=IN IP4 225.224.1.1&#xD;
t=0 0&#xD;
m=video 4002 RTP/AVP  96&#xD;
a=rtpmap:96 H264/90000&#xD;
a=fmtp:96 profile-level-id=42A01E; packetization-mode=1; sprop-parameter-sets=Z0IACpZTBYmI,aMljiA==&#xD;
m=audio 4004 RTP/AVP  98&#xD;
a=rtpmap:98 AMR/8000&#xD;
a=fmtp:98 octet-align=1&#xD;
</SDP></SessionDescription></ComponentDescription></Acquisition><Acquisition acquisitionID="BBCThree_acq" contentMimeType="application/octet-stream"><ComponentDescription><SessionDescription xsi:type="esg:InlinedSDPType"><SDP>v=0&#xD;
o=cbmshost 2890844526 2890842807 IN IP4 192.168.0.2&#xD;
s=Expway SDP Example&#xD;
i=Example of SDP file for &#xD;
u=http://www.expway.com/&#xD;
c=IN IP4 225.224.1.1&#xD;
t=0 0&#xD;
m=video 4002 RTP/AVP  96&#xD;
a=rtpmap:96 H264/90000&#xD;
a=fmtp:96 profile-level-id=42A01E; packetization-mode=1; sprop-parameter-sets=Z0IACpZTBYmI,aMljiA==&#xD;
m=audio 4004 RTP/AVP  98&#xD;
a=rtpmap:98 AMR/8000&#xD;
a=fmtp:98 octet-align=1&#xD;
</SDP></SessionDescription></ComponentDescription></Acquisition><Acquisition acquisitionID="BBCFour_acq" contentMimeType="application/octet-stream"><ComponentDescription><SessionDescription xsi:type="esg:InlinedSDPType"><SDP>v=0&#xD;
o=cbmshost 2890844526 2890842807 IN IP4 192.168.0.2&#xD;
s=Expway SDP Example&#xD;
i=Example of SDP file for &#xD;
u=http://www.expway.com/&#xD;
c=IN IP4 225.224.1.1&#xD;
t=0 0&#xD;
m=video 4002 RTP/AVP  96&#xD;
a=rtpmap:96 H264/90000&#xD;
a=fmtp:96 profile-level-id=42A01E; packetization-mode=1; sprop-parameter-sets=Z0IACpZTBYmI,aMljiA==&#xD;
m=audio 4004 RTP/AVP  98&#xD;
a=rtpmap:98 AMR/8000&#xD;
a=fmtp:98 octet-align=1&#xD;
</SDP></SessionDescription></ComponentDescription></Acquisition><Acquisition acquisitionID="BBCCBBC_acq" contentMimeType="application/octet-stream"><ComponentDescription><SessionDescription xsi:type="esg:InlinedSDPType"><SDP>v=0&#xD;
o=cbmshost 2890844526 2890842807 IN IP4 192.168.0.2&#xD;
s=Expway SDP Example&#xD;
i=Example of SDP file for &#xD;
u=http://www.expway.com/&#xD;
c=IN IP4 225.224.1.1&#xD;
t=0 0&#xD;
m=video 4002 RTP/AVP  96&#xD;
a=rtpmap:96 H264/90000&#xD;
a=fmtp:96 profile-level-id=42A01E; packetization-mode=1; sprop-parameter-sets=Z0IACpZTBYmI,aMljiA==&#xD;
m=audio 4004 RTP/AVP  98&#xD;
a=rtpmap:98 AMR/8000&#xD;
a=fmtp:98 octet-align=1&#xD;
</SDP></SessionDescription></ComponentDescription></Acquisition><Acquisition acquisitionID="BBCCbeebies_acq" contentMimeType="application/octet-stream"><ComponentDescription><SessionDescription xsi:type="esg:InlinedSDPType"><SDP>v=0&#xD;
o=cbmshost 2890844526 2890842807 IN IP4 192.168.0.2&#xD;
s=Expway SDP Example&#xD;
i=Example of SDP file for &#xD;
u=http://www.expway.com/&#xD;
c=IN IP4 225.224.1.1&#xD;
t=0 0&#xD;
m=video 4002 RTP/AVP  96&#xD;
a=rtpmap:96 H264/90000&#xD;
a=fmtp:96 profile-level-id=42A01E; packetization-mode=1; sprop-parameter-sets=Z0IACpZTBYmI,aMljiA==&#xD;
m=audio 4004 RTP/AVP  98&#xD;
a=rtpmap:98 AMR/8000&#xD;
a=fmtp:98 octet-align=1&#xD;
</SDP></SessionDescription></ComponentDescription></Acquisition><Acquisition acquisitionID="BBCParl_acq" contentMimeType="application/octet-stream"><ComponentDescription><SessionDescription xsi:type="esg:InlinedSDPType"><SDP>v=0&#xD;
o=cbmshost 2890844526 2890842807 IN IP4 192.168.0.2&#xD;
s=Expway SDP Example&#xD;
i=Example of SDP file for &#xD;
u=http://www.expway.com/&#xD;
c=IN IP4 225.224.1.1&#xD;
t=0 0&#xD;
m=video 4002 RTP/AVP  96&#xD;
a=rtpmap:96 H264/90000&#xD;
a=fmtp:96 profile-level-id=42A01E; packetization-mode=1; sprop-parameter-sets=Z0IACpZTBYmI,aMljiA==&#xD;
m=audio 4004 RTP/AVP  98&#xD;
a=rtpmap:98 AMR/8000&#xD;
a=fmtp:98 octet-align=1&#xD;
</SDP></SessionDescription></ComponentDescription></Acquisition><Acquisition acquisitionID="BBCWrld_acq" contentMimeType="application/octet-stream"><ComponentDescription><SessionDescription xsi:type="esg:InlinedSDPType"><SDP>v=0&#xD;
o=cbmshost 2890844526 2890842807 IN IP4 192.168.0.2&#xD;
s=Expway SDP Example&#xD;
i=Example of SDP file for &#xD;
u=http://www.expway.com/&#xD;
c=IN IP4 225.224.1.1&#xD;
t=0 0&#xD;
m=video 4002 RTP/AVP  96&#xD;
a=rtpmap:96 H264/90000&#xD;
a=fmtp:96 profile-level-id=42A01E; packetization-mode=1; sprop-parameter-sets=Z0IACpZTBYmI,aMljiA==&#xD;
m=audio 4004 RTP/AVP  98&#xD;
a=rtpmap:98 AMR/8000&#xD;
a=fmtp:98 octet-align=1&#xD;
</SDP></SessionDescription></ComponentDescription></Acquisition><Acquisition acquisitionID="BBCROne_acq" contentMimeType="application/octet-stream"><ComponentDescription><SessionDescription xsi:type="esg:InlinedSDPType"><SDP>v=0&#xD;
o=cbmshost 2890844526 2890842807 IN IP4 192.168.0.2&#xD;
s=Expway SDP Example&#xD;
i=Example of SDP file for &#xD;
u=http://www.expway.com/&#xD;
c=IN IP4 225.224.1.1&#xD;
t=0 0&#xD;
m=video 4002 RTP/AVP  96&#xD;
a=rtpmap:96 H264/90000&#xD;
a=fmtp:96 profile-level-id=42A01E; packetization-mode=1; sprop-parameter-sets=Z0IACpZTBYmI,aMljiA==&#xD;
m=audio 4004 RTP/AVP  98&#xD;
a=rtpmap:98 AMR/8000&#xD;
a=fmtp:98 octet-align=1&#xD;
</SDP></SessionDescription></ComponentDescription></Acquisition><Acquisition acquisitionID="BBCRTwo_acq" contentMimeType="application/octet-stream"><ComponentDescription><SessionDescription xsi:type="esg:InlinedSDPType"><SDP>v=0&#xD;
o=cbmshost 2890844526 2890842807 IN IP4 192.168.0.2&#xD;
s=Expway SDP Example&#xD;
i=Example of SDP file for &#xD;
u=http://www.expway.com/&#xD;
c=IN IP4 225.224.1.1&#xD;
t=0 0&#xD;
m=video 4002 RTP/AVP  96&#xD;
a=rtpmap:96 H264/90000&#xD;
a=fmtp:96 profile-level-id=42A01E; packetization-mode=1; sprop-parameter-sets=Z0IACpZTBYmI,aMljiA==&#xD;
m=audio 4004 RTP/AVP  98&#xD;
a=rtpmap:98 AMR/8000&#xD;
a=fmtp:98 octet-align=1&#xD;
</SDP></SessionDescription></ComponentDescription></Acquisition><Acquisition acquisitionID="BBCRThree_acq" contentMimeType="application/octet-stream"><ComponentDescription><SessionDescription xsi:type="esg:InlinedSDPType"><SDP>v=0&#xD;
o=cbmshost 2890844526 2890842807 IN IP4 192.168.0.2&#xD;
s=Expway SDP Example&#xD;
i=Example of SDP file for &#xD;
u=http://www.expway.com/&#xD;
c=IN IP4 225.224.1.1&#xD;
t=0 0&#xD;
m=video 4002 RTP/AVP  96&#xD;
a=rtpmap:96 H264/90000&#xD;
a=fmtp:96 profile-level-id=42A01E; packetization-mode=1; sprop-parameter-sets=Z0IACpZTBYmI,aMljiA==&#xD;
m=audio 4004 RTP/AVP  98&#xD;
a=rtpmap:98 AMR/8000&#xD;
a=fmtp:98 octet-align=1&#xD;
</SDP></SessionDescription></ComponentDescription></Acquisition><Acquisition acquisitionID="BBCRFour_acq" contentMimeType="application/octet-stream"><ComponentDescription><SessionDescription xsi:type="esg:InlinedSDPType"><SDP>v=0&#xD;
o=cbmshost 2890844526 2890842807 IN IP4 192.168.0.2&#xD;
s=Expway SDP Example&#xD;
i=Example of SDP file for &#xD;
u=http://www.expway.com/&#xD;
c=IN IP4 225.224.1.1&#xD;
t=0 0&#xD;
m=video 4002 RTP/AVP  96&#xD;
a=rtpmap:96 H264/90000&#xD;
a=fmtp:96 profile-level-id=42A01E; packetization-mode=1; sprop-parameter-sets=Z0IACpZTBYmI,aMljiA==&#xD;
m=audio 4004 RTP/AVP  98&#xD;
a=rtpmap:98 AMR/8000&#xD;
a=fmtp:98 octet-align=1&#xD;
</SDP></SessionDescription></ComponentDescription></Acquisition><Acquisition acquisitionID="BBCRFiveL_acq" contentMimeType="application/octet-stream"><ComponentDescription><SessionDescription xsi:type="esg:InlinedSDPType"><SDP>v=0&#xD;
o=cbmshost 2890844526 2890842807 IN IP4 192.168.0.2&#xD;
s=Expway SDP Example&#xD;
i=Example of SDP file for &#xD;
u=http://www.expway.com/&#xD;
c=IN IP4 225.224.1.1&#xD;
t=0 0&#xD;
m=video 4002 RTP/AVP  96&#xD;
a=rtpmap:96 H264/90000&#xD;
a=fmtp:96 profile-level-id=42A01E; packetization-mode=1; sprop-parameter-sets=Z0IACpZTBYmI,aMljiA==&#xD;
m=audio 4004 RTP/AVP  98&#xD;
a=rtpmap:98 AMR/8000&#xD;
a=fmtp:98 octet-align=1&#xD;
</SDP></SessionDescription></ComponentDescription></Acquisition><Acquisition acquisitionID="BBCRFiveX_acq" contentMimeType="application/octet-stream"><ComponentDescription><SessionDescription xsi:type="esg:InlinedSDPType"><SDP>v=0&#xD;
o=cbmshost 2890844526 2890842807 IN IP4 192.168.0.2&#xD;
s=Expway SDP Example&#xD;
i=Example of SDP file for &#xD;
u=http://www.expway.com/&#xD;
c=IN IP4 225.224.1.1&#xD;
t=0 0&#xD;
m=video 4002 RTP/AVP  96&#xD;
a=rtpmap:96 H264/90000&#xD;
a=fmtp:96 profile-level-id=42A01E; packetization-mode=1; sprop-parameter-sets=Z0IACpZTBYmI,aMljiA==&#xD;
m=audio 4004 RTP/AVP  98&#xD;
a=rtpmap:98 AMR/8000&#xD;
a=fmtp:98 octet-align=1&#xD;
</SDP></SessionDescription></ComponentDescription></Acquisition><Acquisition acquisitionID="BBCSixMU_acq" contentMimeType="application/octet-stream"><ComponentDescription><SessionDescription xsi:type="esg:InlinedSDPType"><SDP>v=0&#xD;
o=cbmshost 2890844526 2890842807 IN IP4 192.168.0.2&#xD;
s=Expway SDP Example&#xD;
i=Example of SDP file for &#xD;
u=http://www.expway.com/&#xD;
c=IN IP4 225.224.1.1&#xD;
t=0 0&#xD;
m=video 4002 RTP/AVP  96&#xD;
a=rtpmap:96 H264/90000&#xD;
a=fmtp:96 profile-level-id=42A01E; packetization-mode=1; sprop-parameter-sets=Z0IACpZTBYmI,aMljiA==&#xD;
m=audio 4004 RTP/AVP  98&#xD;
a=rtpmap:98 AMR/8000&#xD;
a=fmtp:98 octet-align=1&#xD;
</SDP></SessionDescription></ComponentDescription></Acquisition><Acquisition acquisitionID="OneXtra_acq" contentMimeType="application/octet-stream"><ComponentDescription><SessionDescription xsi:type="esg:InlinedSDPType"><SDP>v=0&#xD;
o=cbmshost 2890844526 2890842807 IN IP4 192.168.0.2&#xD;
s=Expway SDP Example&#xD;
i=Example of SDP file for &#xD;
u=http://www.expway.com/&#xD;
c=IN IP4 225.224.1.1&#xD;
t=0 0&#xD;
m=video 4002 RTP/AVP  96&#xD;
a=rtpmap:96 H264/90000&#xD;
a=fmtp:96 profile-level-id=42A01E; packetization-mode=1; sprop-parameter-sets=Z0IACpZTBYmI,aMljiA==&#xD;
m=audio 4004 RTP/AVP  98&#xD;
a=rtpmap:98 AMR/8000&#xD;
a=fmtp:98 octet-align=1&#xD;
</SDP></SessionDescription></ComponentDescription></Acquisition><Acquisition acquisitionID="BBCSeven_acq" contentMimeType="application/octet-stream"><ComponentDescription><SessionDescription xsi:type="esg:InlinedSDPType"><SDP>v=0&#xD;
o=cbmshost 2890844526 2890842807 IN IP4 192.168.0.2&#xD;
s=Expway SDP Example&#xD;
i=Example of SDP file for &#xD;
u=http://www.expway.com/&#xD;
c=IN IP4 225.224.1.1&#xD;
t=0 0&#xD;
m=video 4002 RTP/AVP  96&#xD;
a=rtpmap:96 H264/90000&#xD;
a=fmtp:96 profile-level-id=42A01E; packetization-mode=1; sprop-parameter-sets=Z0IACpZTBYmI,aMljiA==&#xD;
m=audio 4004 RTP/AVP  98&#xD;
a=rtpmap:98 AMR/8000&#xD;
a=fmtp:98 octet-align=1&#xD;
</SDP></SessionDescription></ComponentDescription></Acquisition><Acquisition acquisitionID="BBCAsian_acq" contentMimeType="application/octet-stream"><ComponentDescription><SessionDescription xsi:type="esg:InlinedSDPType"><SDP>v=0&#xD;
o=cbmshost 2890844526 2890842807 IN IP4 192.168.0.2&#xD;
s=Expway SDP Example&#xD;
i=Example of SDP file for &#xD;
u=http://www.expway.com/&#xD;
c=IN IP4 225.224.1.1&#xD;
t=0 0&#xD;
m=video 4002 RTP/AVP  96&#xD;
a=rtpmap:96 H264/90000&#xD;
a=fmtp:96 profile-level-id=42A01E; packetization-mode=1; sprop-parameter-sets=Z0IACpZTBYmI,aMljiA==&#xD;
m=audio 4004 RTP/AVP  98&#xD;
a=rtpmap:98 AMR/8000&#xD;
a=fmtp:98 octet-align=1&#xD;
</SDP></SessionDescription></ComponentDescription></Acquisition></AcquisitionTable></ESG></ESGMain>